educommon/__init__.py
educommon/thread_data.py
educommon/about/README.rst
educommon/about/__init__.py
educommon/about/apps.py
educommon/about/utils.py
educommon/about/static/edu_about/barsgroup.png
educommon/about/ui/__init__.py
educommon/about/ui/about-window.js
educommon/about/ui/actions.py
educommon/about/ui/common-tab.html
educommon/about/ui/packages-tab.js
educommon/about/ui/postgresql-extensions-tab.js
educommon/about/ui/ui.py
educommon/async_task/__init__.py
educommon/async_task/actions.py
educommon/async_task/apps.py
educommon/async_task/consts.py
educommon/async_task/exceptions.py
educommon/async_task/helpers.py
educommon/async_task/locker.py
educommon/async_task/models.py
educommon/async_task/tasks.py
educommon/async_task/ui.py
educommon/async_task/migrations/0001_initial.py
educommon/async_task/migrations/0002_task_type_and_status_data.py
educommon/async_task/migrations/0003_alter_runningtask_options.py
educommon/async_task/migrations/__init__.py
educommon/async_task/templates/ui-js/async-task-list-win.js
educommon/async_task/templates/ui-js/async-task-revoke.js
educommon/async_task/templates/ui-js/async-task-view-win.js
educommon/async_tasks/__init__.py
educommon/async_tasks/apps.py
educommon/async_tasks/exceptions.py
educommon/async_tasks/locks.py
educommon/async_tasks/models.py
educommon/async_tasks/statuses.py
educommon/async_tasks/tasks.py
educommon/async_tasks/fixtures/initial_data.json
educommon/async_tasks/migrations/0001_initial.py
educommon/async_tasks/migrations/0002_load_initial_data.py
educommon/async_tasks/migrations/__init__.py
educommon/audit_log/README.rst
educommon/audit_log/__init__.py
educommon/audit_log/actions.py
educommon/audit_log/app_meta.py
educommon/audit_log/apps.py
educommon/audit_log/constants.py
educommon/audit_log/helpers.py
educommon/audit_log/middleware.py
educommon/audit_log/models.py
educommon/audit_log/permissions.py
educommon/audit_log/proxies.py
educommon/audit_log/routers.py
educommon/audit_log/ui.py
educommon-3.29.0.dist-info/METADATA
educommon-3.29.0.dist-info/WHEEL
educommon-3.29.0.dist-info/top_level.txt
educommon-3.29.0.dist-info/RECORD
