Metadata-Version: 2.4
Name: educommon
Version: 3.29.0
Summary: Общая кодовая база для проектов БЦ Образование
Author-email: BARS Group <education_dev@bars-open.ru>
Project-URL: Homepage, https://stash.bars-open.ru/projects/EDUBASE/repos/educommon/browse
Project-URL: Repository, https://stash.bars-open.ru/scm/edubase/educommon.git
Classifier: Intended Audience :: Developers
Classifier: Environment :: Web Environment
Classifier: Natural Language :: Russian
Classifier: Natural Language :: English
Classifier: Operating System :: OS Independent
Classifier: Development Status :: 5 - Production/Stable
Classifier: Programming Language :: Python
Classifier: Programming Language :: Python :: 3.9
Classifier: Framework :: Django :: 2.2
Classifier: Framework :: Django :: 3.0
Classifier: Framework :: Django :: 3.1
Classifier: Framework :: Django :: 3.2
Classifier: Framework :: Django :: 4.0
Classifier: Framework :: Django :: 4.1
Requires-Python: >=3.9
Requires-Dist: packaging<25,>=21
Requires-Dist: Django<5.0,>=3.1
Requires-Dist: django-mptt
Requires-Dist: python-dateutil
Requires-Dist: termcolor
Requires-Dist: django-sendfile
Requires-Dist: requests
Requires-Dist: celery
Requires-Dist: spyne
Requires-Dist: xlsxwriter<1,>=0.9.3
Requires-Dist: python-magic==0.4.15
Requires-Dist: pygost==3.15
Requires-Dist: m3-db-utils>=0.3.13
Requires-Dist: m3-django-compatibility<2,>=1.12.0
Requires-Dist: m3-core<3,>=2.2.16
Requires-Dist: m3-ui<3,>=2.2.116
Requires-Dist: m3-objectpack<3,>=2.2.49
Requires-Dist: m3-simple-report<2,>=1.4.1
Requires-Dist: m3-spyne-smev<2,>=0.2.4
Requires-Dist: distro<2,>=1.3.0; sys_platform == "linux"
Provides-Extra: dev
Requires-Dist: isort==5.12.0; extra == "dev"
Requires-Dist: ruff==0.12.1; extra == "dev"
Requires-Dist: flake8<7,>=4.0.1; extra == "dev"
Requires-Dist: pytest<8,>=3.2.5; extra == "dev"
Requires-Dist: pytest-cov<5; extra == "dev"
Provides-Extra: docs
Requires-Dist: sphinx<7.5,>=7; extra == "docs"
Requires-Dist: sphinx-autodoc-typehints<2.5,>=2; extra == "docs"
Requires-Dist: myst-parser<3.2,>=3; extra == "docs"
Requires-Dist: sphinx_design<0.7,>=0.6; extra == "docs"
